<?xml version="1.0" encoding="UTF-8"?><record_update table="sp_instance">
    <sp_instance action="DELETE">
        <active>true</active>
        <class_name/>
        <color>default</color>
        <css/>
        <glyph/>
        <id/>
        <order>2</order>
        <roles/>
        <short_description/>
        <size>md</size>
        <sp_column display_value="1">e2063a2b2ff5f11062655fd62799b679</sp_column>
        <sp_widget display_value="Knowledge Facet Header">7cb8fab1db12220099f93691f0b8f535</sp_widget>
        <sys_class_name>sp_instance</sys_class_name>
        <sys_created_by>admin</sys_created_by>
        <sys_created_on>2023-10-16 18:20:29</sys_created_on>
        <sys_id>ae063a2b2ff5f11062655fd62799b67d</sys_id>
        <sys_mod_count>0</sys_mod_count>
        <sys_name/>
        <sys_package display_value="MultiverseNow" source="x_903520_rpg">ba5b0fd22f71311062655fd62799b6d1</sys_package>
        <sys_policy/>
        <sys_scope display_value="MultiverseNow">ba5b0fd22f71311062655fd62799b6d1</sys_scope>
        <sys_update_name>sp_instance_ae063a2b2ff5f11062655fd62799b67d</sys_update_name>
        <sys_updated_by>admin</sys_updated_by>
        <sys_updated_on>2023-10-16 18:20:29</sys_updated_on>
        <title/>
        <url/>
        <widget_parameters/>
    </sp_instance>
    <sys_translated_text action="DELETE" query="documentkey=ae063a2b2ff5f11062655fd62799b67d"/>
    <sys_update_version action="INSERT_OR_UPDATE">
        <action>DELETE</action>
        <application display_value="MultiverseNow">ba5b0fd22f71311062655fd62799b6d1</application>
        <file_path/>
        <instance_id>13e69defdb22ddd842b321c4059619e0</instance_id>
        <instance_name>dev141910</instance_name>
        <name>sp_instance_ae063a2b2ff5f11062655fd62799b67d</name>
        <payload><![CDATA[<?xml version="1.0" encoding="UTF-8"?><record_update table="sp_instance"><sp_instance action="INSERT_OR_UPDATE"><active>true</active><class_name/><color>default</color><css/><glyph/><id/><order>2</order><roles/><short_description/><size>md</size><sp_column display_value="1">e2063a2b2ff5f11062655fd62799b679</sp_column><sp_widget display_value="Knowledge Facet Header">7cb8fab1db12220099f93691f0b8f535</sp_widget><sys_class_name>sp_instance</sys_class_name><sys_created_by>admin</sys_created_by><sys_created_on>2023-10-16 18:20:29</sys_created_on><sys_id>ae063a2b2ff5f11062655fd62799b67d</sys_id><sys_mod_count>0</sys_mod_count><sys_name/><sys_package display_value="MultiverseNow" source="x_903520_rpg">ba5b0fd22f71311062655fd62799b6d1</sys_package><sys_policy/><sys_scope display_value="MultiverseNow">ba5b0fd22f71311062655fd62799b6d1</sys_scope><sys_update_name>sp_instance_ae063a2b2ff5f11062655fd62799b67d</sys_update_name><sys_updated_by>admin</sys_updated_by><sys_updated_on>2023-10-16 18:20:29</sys_updated_on><title/><url/><widget_parameters/></sp_instance><sys_translated_text action="delete_multiple" query="documentkey=ae063a2b2ff5f11062655fd62799b67d"/></record_update>]]></payload>
        <payload_hash>-341995704</payload_hash>
        <record_name/>
        <reverted_from/>
        <source>7e5b0fd22f71311062655fd62799b6d3</source>
        <source_table>sys_update_set</source_table>
        <state>previous</state>
        <sys_created_by>admin</sys_created_by>
        <sys_created_on>2023-10-16 18:20:29</sys_created_on>
        <sys_id>6e063a2b2ff5f11062655fd62799b67f</sys_id>
        <sys_mod_count>0</sys_mod_count>
        <sys_recorded_at>18b39b7d1720000001</sys_recorded_at>
        <sys_updated_by>admin</sys_updated_by>
        <sys_updated_on>2023-10-16 18:20:29</sys_updated_on>
        <type>Instance</type>
        <update_guid>a2063a2be9f5f1105f7eb95c34d8c77f</update_guid>
        <update_guid_history>a2063a2be9f5f1105f7eb95c34d8c77f:-341995704</update_guid_history>
    </sys_update_version>
    <sys_metadata_delete action="INSERT_OR_UPDATE">
        <sys_audit_delete display_value="">3a4636ab2ff5f11062655fd62799b67f</sys_audit_delete>
        <sys_class_name>sys_metadata_delete</sys_class_name>
        <sys_created_by>admin</sys_created_by>
        <sys_created_on>2023-10-16 18:21:36</sys_created_on>
        <sys_db_object display_value="" name="sp_instance">sp_instance</sys_db_object>
        <sys_id>343ef29a34ae4a35b62c21402a7245e1</sys_id>
        <sys_metadata>ae063a2b2ff5f11062655fd62799b67d</sys_metadata>
        <sys_mod_count>0</sys_mod_count>
        <sys_name/>
        <sys_package display_value="MultiverseNow" source="x_903520_rpg">ba5b0fd22f71311062655fd62799b6d1</sys_package>
        <sys_parent/>
        <sys_policy/>
        <sys_scope display_value="MultiverseNow">ba5b0fd22f71311062655fd62799b6d1</sys_scope>
        <sys_scope_delete display_value="">9430b02c5a5e44e69daf0c2ab3fbef51</sys_scope_delete>
        <sys_update_name>sp_instance_ae063a2b2ff5f11062655fd62799b67d</sys_update_name>
        <sys_update_version display_value="sp_instance_ae063a2b2ff5f11062655fd62799b67d">6e063a2b2ff5f11062655fd62799b67f</sys_update_version>
        <sys_updated_by>admin</sys_updated_by>
        <sys_updated_on>2023-10-16 18:21:36</sys_updated_on>
    </sys_metadata_delete>
</record_update>
